LICENSE
nautobot_plugin_ip_services/__init__.py
nautobot_plugin_ip_services/models.py
nautobot_plugin_ip_services/navigation.py
nautobot_plugin_ip_services/template_content.py
nautobot_plugin_ip_services/templates/nautobot_plugin_ip_services/ipaddress_services.html
nautobot_plugin_ip_services/tests/__init__.py
nautobot_plugin_ip_services/tests/test_models.py
nautobot_plugin_ip_services/tests/test_nautobot_plugin_ip_services.py
nautobot_plugin_ip_services/tests/test_views.py
nautobot_plugin_ip_services/urls.py
nautobot_plugin_ip_services/views.py
nautobot_plugin_ip_services-1.0.5.dist-info/LICENSE
nautobot_plugin_ip_services-1.0.5.dist-info/WHEEL
nautobot_plugin_ip_services-1.0.5.dist-info/METADATA
nautobot_plugin_ip_services-1.0.5.dist-info/RECORD
