Metadata-Version: 2.1
Name: nautobot-plugin-ip-services
Version: 1.0.5
Summary: View/Manage Services from IPAM
Home-page: https://github.com/mamullen13316/nautobot-plugin-ip-services
Author: Matt Mullen
Author-email: mullenmd@gmail.com
Requires-Python: >=3.8,<4.0
Classifier: Programming Language :: Python :: 3
Classifier: Programming Language :: Python :: 3.10
Classifier: Programming Language :: Python :: 3.8
Classifier: Programming Language :: Python :: 3.9
Project-URL: Repository, https://github.com/mamullen13316/nautobot-plugin-ip-services
